VeritransPay-1.0.dist-info/DESCRIPTION.rst
VeritransPay-1.0.dist-info/METADATA
VeritransPay-1.0.dist-info/RECORD
VeritransPay-1.0.dist-info/WHEEL
VeritransPay-1.0.dist-info/metadata.json
VeritransPay-1.0.dist-info/top_level.txt
veritranspay/__init__.py
veritranspay/constraints.py
veritranspay/helpers.py
veritranspay/mixins.py
veritranspay/payment_types.py
veritranspay/request.py
veritranspay/validators.py
veritranspay/veritrans.py
veritranspay/response/__init__.py
veritranspay/response/response.py
veritranspay/response/status.py
