Metadata-Version: 2.0
Name: VeritransPay
Version: 1.0
Summary: Veritrans.co.id API Client Library 
Home-page: https://github.com/derekjamescurtis/veritranspay
Author: Derek J. Curtis
Author-email: derek.curtis@apps-foundry.com
License: BSD
Platform: any
Classifier: Development Status :: 3 - Alpha
Classifier: Programming Language :: Python :: 2.7
Classifier: Programming Language :: Python :: 3.3
Classifier: Programming Language :: Python :: 3.4
Requires-Dist: requests (>=2.3.0)
